{
    "unique_key": "8025b1f0-c571-4750-a815-300f72ec5d1f",
    "sorted_schedule": {
        "schedule": [
            {
                "section": "CSCI-160-001",
                "timeslot": "M - 11:15AM",
                "faculty1": "Weinberg, Eric G",
                "room": "228",
                "minCredit": "4",
                "unwanted_timeslots": [],
                "secCap": "16",
                "bldg": "RCE",
                "avoid_classes": [],
                "hold_value": 0
            },
            {
                "section": "CSCI-160-001",
                "timeslot": "W - 11:15AM",
                "faculty1": "Weinberg, Eric G",
                "room": "228",
                "minCredit": "4",
                "unwanted_timeslots": [],
                "secCap": "16",
                "bldg": "RCE",
                "avoid_classes": [],
                "hold_value": 0
            },
            {
                "section": "CSCI-160-001",
                "timeslot": "F - 11:15AM",
                "faculty1": "Weinberg, Eric G",
                "room": "228",
                "minCredit": "4",
                "unwanted_timeslots": [],
                "secCap": "16",
                "bldg": "RCE",
                "avoid_classes": [],
                "hold_value": 0
            },
            {
                "section": "CSCI-200-001",
                "timeslot": "M - 12:20PM",
                "faculty1": "Weinberg, Eric G",
                "room": "228",
                "minCredit": "3",
                "unwanted_timeslots": [],
                "secCap": "16",
                "bldg": "RCE",
                "avoid_classes": [],
                "hold_value": 0
            },
            {
                "section": "CSCI-200-001",
                "timeslot": "W - 12:20PM",
                "faculty1": "Weinberg, Eric G",
                "room": "228",
                "minCredit": "3",
                "unwanted_timeslots": [],
                "secCap": "16",
                "bldg": "RCE",
                "avoid_classes": [],
                "hold_value": 0
            },
            {
                "section": "CSCI-200-001",
                "timeslot": "F - 12:20PM",
                "faculty1": "Weinberg, Eric G",
                "room": "228",
                "minCredit": "3",
                "unwanted_timeslots": [],
                "secCap": "16",
                "bldg": "RCE",
                "avoid_classes": [],
                "hold_value": 0
            },
            {
                "section": "CSCI-210-001",
                "timeslot": "Tu - 2:00PM",
                "faculty1": "Weinberg, Eric G",
                "room": "228",
                "minCredit": "3",
                "unwanted_timeslots": [],
                "secCap": "16",
                "bldg": "RCE",
                "avoid_classes": [],
                "hold_value": 0
            },
            {
                "section": "CSCI-210-001",
                "timeslot": "Th - 2:00PM",
                "faculty1": "Weinberg, Eric G",
                "room": "228",
                "minCredit": "3",
                "unwanted_timeslots": [],
                "secCap": "16",
                "bldg": "RCE",
                "avoid_classes": [],
                "hold_value": 0
            },
            {
                "section": "CSCI-499-001",
                "timeslot": "M - 10:10AM",
                "faculty1": "Weinberg, Eric G",
                "room": "233",
                "minCredit": "3",
                "unwanted_timeslots": [],
                "secCap": "24",
                "bldg": "RCE",
                "avoid_classes": [],
                "hold_value": 0
            },
            {
                "section": "CSCI-499-001",
                "timeslot": "W - 10:10AM",
                "faculty1": "Weinberg, Eric G",
                "room": "233",
                "minCredit": "3",
                "unwanted_timeslots": [],
                "secCap": "24",
                "bldg": "RCE",
                "avoid_classes": [],
                "hold_value": 0
            },
            {
                "section": "CSCI-499-001",
                "timeslot": "F - 10:10AM",
                "faculty1": "Weinberg, Eric G",
                "room": "233",
                "minCredit": "3",
                "unwanted_timeslots": [],
                "secCap": "24",
                "bldg": "RCE",
                "avoid_classes": [],
                "hold_value": 0
            },
            {
                "section": "ENGR-150-001",
                "timeslot": "Tu - 12:30PM",
                "faculty1": "Vanderfleet, Emily J",
                "room": "438",
                "minCredit": "4",
                "unwanted_timeslots": [],
                "secCap": "16",
                "bldg": "FAC",
                "avoid_classes": [],
                "hold_value": 0
            },
            {
                "section": "ENGR-150-001",
                "timeslot": "Th - 12:30PM",
                "faculty1": "Vanderfleet, Emily J",
                "room": "438",
                "minCredit": "4",
                "unwanted_timeslots": [],
                "secCap": "16",
                "bldg": "FAC",
                "avoid_classes": [],
                "hold_value": 0
            },
            {
                "section": "ENGR-250-001",
                "timeslot": "M - 2:30PM",
                "faculty1": "Harned, Richard C",
                "room": "233",
                "minCredit": "4",
                "unwanted_timeslots": [],
                "secCap": "16",
                "bldg": "RCE",
                "avoid_classes": [],
                "hold_value": 0
            },
            {
                "section": "ENGR-250-001",
                "timeslot": "W - 2:30PM",
                "faculty1": "Harned, Richard C",
                "room": "233",
                "minCredit": "4",
                "unwanted_timeslots": [],
                "secCap": "16",
                "bldg": "RCE",
                "avoid_classes": [],
                "hold_value": 0
            },
            {
                "section": "ENGR-250-001",
                "timeslot": "F - 2:30PM",
                "faculty1": "Harned, Richard C",
                "room": "233",
                "minCredit": "4",
                "unwanted_timeslots": [],
                "secCap": "16",
                "bldg": "RCE",
                "avoid_classes": [],
                "hold_value": 0
            },
            {
                "section": "ENGR-320-001",
                "timeslot": "Tu - 2:00PM",
                "faculty1": "Vanderfleet, Emily J",
                "room": "233",
                "minCredit": "4",
                "unwanted_timeslots": [],
                "secCap": "16",
                "bldg": "RCE",
                "avoid_classes": [],
                "hold_value": 0
            },
            {
                "section": "ENGR-320-001",
                "timeslot": "Th - 2:00PM",
                "faculty1": "Vanderfleet, Emily J",
                "room": "233",
                "minCredit": "4",
                "unwanted_timeslots": [],
                "secCap": "16",
                "bldg": "RCE",
                "avoid_classes": [],
                "hold_value": 0
            },
            {
                "section": "ENGR-365-001",
                "timeslot": "Tu - 8:00AM",
                "faculty1": "Lee, Sheldon H",
                "room": "233",
                "minCredit": "4",
                "unwanted_timeslots": [],
                "secCap": "16",
                "bldg": "RCE",
                "avoid_classes": [],
                "hold_value": 0
            },
            {
                "section": "ENGR-365-001",
                "timeslot": "Th - 8:00AM",
                "faculty1": "Lee, Sheldon H",
                "room": "233",
                "minCredit": "4",
                "unwanted_timeslots": [],
                "secCap": "16",
                "bldg": "RCE",
                "avoid_classes": [],
                "hold_value": 0
            },
            {
                "section": "ENGR-370-001",
                "timeslot": "Tu - 3:30PM",
                "faculty1": "Harned, Richard C",
                "room": "233",
                "minCredit": "4",
                "unwanted_timeslots": [],
                "secCap": "16",
                "bldg": "RCE",
                "avoid_classes": [],
                "hold_value": 0
            },
            {
                "section": "ENGR-370-001",
                "timeslot": "Th - 3:30PM",
                "faculty1": "Harned, Richard C",
                "room": "233",
                "minCredit": "4",
                "unwanted_timeslots": [],
                "secCap": "16",
                "bldg": "RCE",
                "avoid_classes": [],
                "hold_value": 0
            },
            {
                "section": "ENGR-489-001",
                "timeslot": "Tu - 9:30AM",
                "faculty1": "nan",
                "room": "ARRG",
                "minCredit": "3",
                "unwanted_timeslots": [],
                "secCap": "16",
                "bldg": "ARRG",
                "avoid_classes": [],
                "hold_value": 0
            },
            {
                "section": "ENGR-489-001",
                "timeslot": "Th - 9:30AM",
                "faculty1": "nan",
                "room": "ARRG",
                "minCredit": "3",
                "unwanted_timeslots": [],
                "secCap": "16",
                "bldg": "ARRG",
                "avoid_classes": [],
                "hold_value": 0
            },
            {
                "section": "ENGR-499-001",
                "timeslot": "M - 3:35PM",
                "faculty1": "Harned, Richard C",
                "room": "233",
                "minCredit": "3",
                "unwanted_timeslots": [],
                "secCap": "24",
                "bldg": "RCE",
                "avoid_classes": [],
                "hold_value": 0
            },
            {
                "section": "ENGR-499-001",
                "timeslot": "W - 3:35PM",
                "faculty1": "Harned, Richard C",
                "room": "233",
                "minCredit": "3",
                "unwanted_timeslots": [],
                "secCap": "24",
                "bldg": "RCE",
                "avoid_classes": [],
                "hold_value": 0
            },
            {
                "section": "ENGR-499-001",
                "timeslot": "F - 3:35PM",
                "faculty1": "Harned, Richard C",
                "room": "233",
                "minCredit": "3",
                "unwanted_timeslots": [],
                "secCap": "24",
                "bldg": "RCE",
                "avoid_classes": [],
                "hold_value": 0
            },
            {
                "section": "MATH-091-001",
                "timeslot": "Tu - 3:30PM",
                "faculty1": "Gaedy, Beth M",
                "room": "314",
                "minCredit": "3",
                "unwanted_timeslots": [],
                "secCap": "24",
                "bldg": "MRC",
                "avoid_classes": [],
                "hold_value": 0
            },
            {
                "section": "MATH-091-001",
                "timeslot": "Th - 3:30PM",
                "faculty1": "Gaedy, Beth M",
                "room": "314",
                "minCredit": "3",
                "unwanted_timeslots": [],
                "secCap": "24",
                "bldg": "MRC",
                "avoid_classes": [],
                "hold_value": 0
            },
            {
                "section": "MATH-112-001",
                "timeslot": "M - 9:05AM",
                "faculty1": "Wodzak, Michael A",
                "room": "346",
                "minCredit": "3",
                "unwanted_timeslots": [],
                "secCap": "30",
                "bldg": "MRC",
                "avoid_classes": [],
                "hold_value": 0
            },
            {
                "section": "MATH-112-001",
                "timeslot": "W - 9:05AM",
                "faculty1": "Wodzak, Michael A",
                "room": "346",
                "minCredit": "3",
                "unwanted_timeslots": [],
                "secCap": "30",
                "bldg": "MRC",
                "avoid_classes": [],
                "hold_value": 0
            },
            {
                "section": "MATH-112-001",
                "timeslot": "F - 9:05AM",
                "faculty1": "Wodzak, Michael A",
                "room": "346",
                "minCredit": "3",
                "unwanted_timeslots": [],
                "secCap": "30",
                "bldg": "MRC",
                "avoid_classes": [],
                "hold_value": 0
            },
            {
                "section": "MATH-113-001",
                "timeslot": "M - 3:35PM",
                "faculty1": "Wodzak, Michael A",
                "room": "346",
                "minCredit": "3",
                "unwanted_timeslots": [],
                "secCap": "30",
                "bldg": "MRC",
                "avoid_classes": [],
                "hold_value": 0
            },
            {
                "section": "MATH-113-001",
                "timeslot": "W - 3:35PM",
                "faculty1": "Wodzak, Michael A",
                "room": "346",
                "minCredit": "3",
                "unwanted_timeslots": [],
                "secCap": "30",
                "bldg": "MRC",
                "avoid_classes": [],
                "hold_value": 0
            },
            {
                "section": "MATH-113-001",
                "timeslot": "F - 3:35PM",
                "faculty1": "Wodzak, Michael A",
                "room": "346",
                "minCredit": "3",
                "unwanted_timeslots": [],
                "secCap": "30",
                "bldg": "MRC",
                "avoid_classes": [],
                "hold_value": 0
            },
            {
                "section": "MATH-130-001",
                "timeslot": "M - 9:05AM",
                "faculty1": "TBD",
                "room": "314",
                "minCredit": "3",
                "unwanted_timeslots": [],
                "secCap": "24",
                "bldg": "MRC",
                "avoid_classes": [],
                "hold_value": 0
            },
            {
                "section": "MATH-130-001",
                "timeslot": "W - 9:05AM",
                "faculty1": "TBD",
                "room": "314",
                "minCredit": "3",
                "unwanted_timeslots": [],
                "secCap": "24",
                "bldg": "MRC",
                "avoid_classes": [],
                "hold_value": 0
            },
            {
                "section": "MATH-130-001",
                "timeslot": "F - 9:05AM",
                "faculty1": "TBD",
                "room": "314",
                "minCredit": "3",
                "unwanted_timeslots": [],
                "secCap": "24",
                "bldg": "MRC",
                "avoid_classes": [],
                "hold_value": 0
            },
            {
                "section": "MATH-130-002",
                "timeslot": "M - 2:30PM",
                "faculty1": "TBD",
                "room": "nan",
                "minCredit": "3",
                "unwanted_timeslots": [],
                "secCap": "24",
                "bldg": "nan",
                "avoid_classes": [],
                "hold_value": 0
            },
            {
                "section": "MATH-130-002",
                "timeslot": "W - 2:30PM",
                "faculty1": "TBD",
                "room": "nan",
                "minCredit": "3",
                "unwanted_timeslots": [],
                "secCap": "24",
                "bldg": "nan",
                "avoid_classes": [],
                "hold_value": 0
            },
            {
                "section": "MATH-130-002",
                "timeslot": "F - 2:30PM",
                "faculty1": "TBD",
                "room": "nan",
                "minCredit": "3",
                "unwanted_timeslots": [],
                "secCap": "24",
                "bldg": "nan",
                "avoid_classes": [],
                "hold_value": 0
            },
            {
                "section": "MATH-155-001",
                "timeslot": "M - 10:10AM",
                "faculty1": "Wodzak, Michael A",
                "room": "378",
                "minCredit": "3",
                "unwanted_timeslots": [],
                "secCap": "24",
                "bldg": "MRC",
                "avoid_classes": [],
                "hold_value": 0
            },
            {
                "section": "MATH-155-001",
                "timeslot": "W - 10:10AM",
                "faculty1": "Wodzak, Michael A",
                "room": "378",
                "minCredit": "3",
                "unwanted_timeslots": [],
                "secCap": "24",
                "bldg": "MRC",
                "avoid_classes": [],
                "hold_value": 0
            },
            {
                "section": "MATH-155-001",
                "timeslot": "F - 10:10AM",
                "faculty1": "Wodzak, Michael A",
                "room": "378",
                "minCredit": "3",
                "unwanted_timeslots": [],
                "secCap": "24",
                "bldg": "MRC",
                "avoid_classes": [],
                "hold_value": 0
            },
            {
                "section": "MATH-221-001",
                "timeslot": "M - 12:20PM",
                "faculty1": "Lee, Sheldon H",
                "room": "444",
                "minCredit": "4",
                "unwanted_timeslots": [],
                "secCap": "24",
                "bldg": "MRC",
                "avoid_classes": [],
                "hold_value": 0
            },
            {
                "section": "MATH-221-001",
                "timeslot": "W - 12:20PM",
                "faculty1": "Lee, Sheldon H",
                "room": "444",
                "minCredit": "4",
                "unwanted_timeslots": [],
                "secCap": "24",
                "bldg": "MRC",
                "avoid_classes": [],
                "hold_value": 0
            },
            {
                "section": "MATH-221-001",
                "timeslot": "F - 12:20PM",
                "faculty1": "Lee, Sheldon H",
                "room": "444",
                "minCredit": "4",
                "unwanted_timeslots": [],
                "secCap": "24",
                "bldg": "MRC",
                "avoid_classes": [],
                "hold_value": 0
            },
            {
                "section": "MATH-230-001",
                "timeslot": "Tu - 11:00AM",
                "faculty1": "Lee, Sheldon H",
                "room": "314",
                "minCredit": "4",
                "unwanted_timeslots": [],
                "secCap": "24",
                "bldg": "MRC",
                "avoid_classes": [],
                "hold_value": 0
            },
            {
                "section": "MATH-230-001",
                "timeslot": "Th - 11:00AM",
                "faculty1": "Lee, Sheldon H",
                "room": "314",
                "minCredit": "4",
                "unwanted_timeslots": [],
                "secCap": "24",
                "bldg": "MRC",
                "avoid_classes": [],
                "hold_value": 0
            },
            {
                "section": "MATH-255-001",
                "timeslot": "M - 10:10AM",
                "faculty1": "Lichty, Joshua J",
                "room": "416",
                "minCredit": "3",
                "unwanted_timeslots": [],
                "secCap": "30",
                "bldg": "MRC",
                "avoid_classes": [],
                "hold_value": 0
            },
            {
                "section": "MATH-255-001",
                "timeslot": "W - 10:10AM",
                "faculty1": "Lichty, Joshua J",
                "room": "416",
                "minCredit": "3",
                "unwanted_timeslots": [],
                "secCap": "30",
                "bldg": "MRC",
                "avoid_classes": [],
                "hold_value": 0
            },
            {
                "section": "MATH-255-001",
                "timeslot": "F - 10:10AM",
                "faculty1": "Lichty, Joshua J",
                "room": "416",
                "minCredit": "3",
                "unwanted_timeslots": [],
                "secCap": "30",
                "bldg": "MRC",
                "avoid_classes": [],
                "hold_value": 0
            },
            {
                "section": "MATH-270-001",
                "timeslot": "Tu - 8:00AM",
                "faculty1": "Wodzak, Michael A",
                "room": "444",
                "minCredit": "3",
                "unwanted_timeslots": [],
                "secCap": "30",
                "bldg": "MRC",
                "avoid_classes": [],
                "hold_value": 0
            },
            {
                "section": "MATH-270-001",
                "timeslot": "Th - 8:00AM",
                "faculty1": "Wodzak, Michael A",
                "room": "444",
                "minCredit": "3",
                "unwanted_timeslots": [],
                "secCap": "30",
                "bldg": "MRC",
                "avoid_classes": [],
                "hold_value": 0
            },
            {
                "section": "MATH-344-001",
                "timeslot": "Tu - 9:30AM",
                "faculty1": "Wodzak, Michael A",
                "room": "378",
                "minCredit": "3",
                "unwanted_timeslots": [],
                "secCap": "16",
                "bldg": "MRC",
                "avoid_classes": [],
                "hold_value": 0
            },
            {
                "section": "MATH-344-001",
                "timeslot": "Th - 9:30AM",
                "faculty1": "Wodzak, Michael A",
                "room": "378",
                "minCredit": "3",
                "unwanted_timeslots": [],
                "secCap": "16",
                "bldg": "MRC",
                "avoid_classes": [],
                "hold_value": 0
            },
            {
                "section": "MATH-365-001",
                "timeslot": "M - 1:25PM",
                "faculty1": "Lee, Sheldon H",
                "room": "233",
                "minCredit": "4",
                "unwanted_timeslots": [],
                "secCap": "16",
                "bldg": "RCE",
                "avoid_classes": [],
                "hold_value": 0
            },
            {
                "section": "MATH-365-001",
                "timeslot": "W - 1:25PM",
                "faculty1": "Lee, Sheldon H",
                "room": "233",
                "minCredit": "4",
                "unwanted_timeslots": [],
                "secCap": "16",
                "bldg": "RCE",
                "avoid_classes": [],
                "hold_value": 0
            },
            {
                "section": "MATH-365-001",
                "timeslot": "F - 1:25PM",
                "faculty1": "Lee, Sheldon H",
                "room": "233",
                "minCredit": "4",
                "unwanted_timeslots": [],
                "secCap": "16",
                "bldg": "RCE",
                "avoid_classes": [],
                "hold_value": 0
            },
            {
                "section": "MATH-499-001",
                "timeslot": "Tu - 9:30AM",
                "faculty1": "Lee, Sheldon H",
                "room": "233",
                "minCredit": "3",
                "unwanted_timeslots": [],
                "secCap": "24",
                "bldg": "RCE",
                "avoid_classes": [],
                "hold_value": 0
            },
            {
                "section": "MATH-499-001",
                "timeslot": "Th - 9:30AM",
                "faculty1": "Lee, Sheldon H",
                "room": "233",
                "minCredit": "3",
                "unwanted_timeslots": [],
                "secCap": "24",
                "bldg": "RCE",
                "avoid_classes": [],
                "hold_value": 0
            },
            {
                "section": "PHYS-102-001",
                "timeslot": "M - 8:00AM",
                "faculty1": "Narayanan, Madhavan",
                "room": "229",
                "minCredit": "4",
                "unwanted_timeslots": [],
                "secCap": "18",
                "bldg": "RCE",
                "avoid_classes": [],
                "hold_value": 0
            },
            {
                "section": "PHYS-102-001",
                "timeslot": "W - 8:00AM",
                "faculty1": "Narayanan, Madhavan",
                "room": "229",
                "minCredit": "4",
                "unwanted_timeslots": [],
                "secCap": "18",
                "bldg": "RCE",
                "avoid_classes": [],
                "hold_value": 0
            },
            {
                "section": "PHYS-102-001",
                "timeslot": "F - 8:00AM",
                "faculty1": "Narayanan, Madhavan",
                "room": "229",
                "minCredit": "4",
                "unwanted_timeslots": [],
                "secCap": "18",
                "bldg": "RCE",
                "avoid_classes": [],
                "hold_value": 0
            },
            {
                "section": "PHYS-251-001",
                "timeslot": "M - 3:35PM",
                "faculty1": "Gerig, Anthony L",
                "room": "229",
                "minCredit": "3",
                "unwanted_timeslots": [],
                "secCap": "24",
                "bldg": "RCE",
                "avoid_classes": [],
                "hold_value": 0
            },
            {
                "section": "PHYS-251-001",
                "timeslot": "W - 3:35PM",
                "faculty1": "Gerig, Anthony L",
                "room": "229",
                "minCredit": "3",
                "unwanted_timeslots": [],
                "secCap": "24",
                "bldg": "RCE",
                "avoid_classes": [],
                "hold_value": 0
            },
            {
                "section": "PHYS-251-001",
                "timeslot": "F - 3:35PM",
                "faculty1": "Gerig, Anthony L",
                "room": "229",
                "minCredit": "3",
                "unwanted_timeslots": [],
                "secCap": "24",
                "bldg": "RCE",
                "avoid_classes": [],
                "hold_value": 0
            },
            {
                "section": "PHYS-261-001",
                "timeslot": "M - 9:05AM",
                "faculty1": "Anglehart, Joseph",
                "room": "229",
                "minCredit": "3",
                "unwanted_timeslots": [],
                "secCap": "20",
                "bldg": "RCE",
                "avoid_classes": [],
                "hold_value": 0
            },
            {
                "section": "PHYS-261-001",
                "timeslot": "W - 9:05AM",
                "faculty1": "Anglehart, Joseph",
                "room": "229",
                "minCredit": "3",
                "unwanted_timeslots": [],
                "secCap": "20",
                "bldg": "RCE",
                "avoid_classes": [],
                "hold_value": 0
            },
            {
                "section": "PHYS-261-001",
                "timeslot": "F - 9:05AM",
                "faculty1": "Anglehart, Joseph",
                "room": "229",
                "minCredit": "3",
                "unwanted_timeslots": [],
                "secCap": "20",
                "bldg": "RCE",
                "avoid_classes": [],
                "hold_value": 0
            },
            {
                "section": "CSCI-160-001_one_credit",
                "timeslot": "Th - 11:00AM",
                "faculty1": "Weinberg, Eric G",
                "room": "228",
                "minCredit": "4",
                "unwanted_timeslots": [],
                "hold_value": 0,
                "secCap": "16",
                "bldg": "RCE",
                "avoid_classes": []
            },
            {
                "section": "ENGR-150-001_one_credit",
                "timeslot": "F - 8:00AM",
                "faculty1": "Vanderfleet, Emily J",
                "room": "438",
                "minCredit": "4",
                "unwanted_timeslots": [],
                "hold_value": 0,
                "secCap": "16",
                "bldg": "FAC",
                "avoid_classes": []
            },
            {
                "section": "ENGR-250-001_one_credit",
                "timeslot": "Tu - 3:30PM",
                "faculty1": "Harned, Richard C",
                "room": "233",
                "minCredit": "4",
                "unwanted_timeslots": [],
                "hold_value": 0,
                "secCap": "16",
                "bldg": "RCE",
                "avoid_classes": []
            },
            {
                "section": "ENGR-320-001_one_credit",
                "timeslot": "W - 8:00AM",
                "faculty1": "Vanderfleet, Emily J",
                "room": "233",
                "minCredit": "4",
                "unwanted_timeslots": [],
                "hold_value": 0,
                "secCap": "16",
                "bldg": "RCE",
                "avoid_classes": []
            },
            {
                "section": "ENGR-365-001_one_credit",
                "timeslot": "F - 9:05AM",
                "faculty1": "Lee, Sheldon H",
                "room": "233",
                "minCredit": "4",
                "unwanted_timeslots": [],
                "hold_value": 0,
                "secCap": "16",
                "bldg": "RCE",
                "avoid_classes": []
            },
            {
                "section": "ENGR-370-001_one_credit",
                "timeslot": "Th - 8:00AM",
                "faculty1": "Harned, Richard C",
                "room": "233",
                "minCredit": "4",
                "unwanted_timeslots": [],
                "hold_value": 0,
                "secCap": "16",
                "bldg": "RCE",
                "avoid_classes": []
            },
            {
                "section": "MATH-081-001",
                "timeslot": "W - 12:20PM",
                "faculty1": "Gaedy, Beth M",
                "room": "378",
                "minCredit": "1",
                "unwanted_timeslots": [],
                "hold_value": 0,
                "secCap": "24",
                "bldg": "MRC",
                "avoid_classes": []
            },
            {
                "section": "MATH-083-001",
                "timeslot": "W - 10:10AM",
                "faculty1": "Gaedy, Beth M",
                "room": "378",
                "minCredit": "1",
                "unwanted_timeslots": [],
                "hold_value": 0,
                "secCap": "24",
                "bldg": "MRC",
                "avoid_classes": []
            },
            {
                "section": "MATH-150-001",
                "timeslot": "Th - 12:30PM",
                "faculty1": "Vanderfleet, Emily J",
                "room": "285",
                "minCredit": "1",
                "unwanted_timeslots": [],
                "hold_value": 0,
                "secCap": "15",
                "bldg": "NRC",
                "avoid_classes": []
            },
            {
                "section": "MATH-221-001_one_credit",
                "timeslot": "F - 1:25PM",
                "faculty1": "Lee, Sheldon H",
                "room": "444",
                "minCredit": "4",
                "unwanted_timeslots": [],
                "hold_value": 0,
                "secCap": "24",
                "bldg": "MRC",
                "avoid_classes": []
            },
            {
                "section": "MATH-230-001_one_credit",
                "timeslot": "M - 2:30PM",
                "faculty1": "Lee, Sheldon H",
                "room": "314",
                "minCredit": "4",
                "unwanted_timeslots": [],
                "hold_value": 0,
                "secCap": "24",
                "bldg": "MRC",
                "avoid_classes": []
            },
            {
                "section": "MATH-365-001_one_credit",
                "timeslot": "Tu - 12:30PM",
                "faculty1": "Lee, Sheldon H",
                "room": "233",
                "minCredit": "4",
                "unwanted_timeslots": [],
                "hold_value": 0,
                "secCap": "16",
                "bldg": "RCE",
                "avoid_classes": []
            },
            {
                "section": "PHYS-102-001_one_credit",
                "timeslot": "F - 11:15AM",
                "faculty1": "Narayanan, Madhavan",
                "room": "229",
                "minCredit": "4",
                "unwanted_timeslots": [],
                "hold_value": 0,
                "secCap": "18",
                "bldg": "RCE",
                "avoid_classes": []
            },
            {
                "section": "PHYS-271-001",
                "timeslot": "W - 1:25PM",
                "faculty1": "Anglehart, Joseph",
                "room": "229",
                "minCredit": "1",
                "unwanted_timeslots": [],
                "hold_value": 0,
                "secCap": "14",
                "bldg": "RCE",
                "avoid_classes": []
            }
        ],
        "score": 68700,
        "algorithm": "PuLP",
        "slot_differences": 0
    },
    "calendar_events": [
        {
            "section_name": "CSCI-160-001",
            "start": "2023-12-06T11:15:00",
            "end": "2023-12-06T12:15:00",
            "faculty1": "Weinberg, Eric G",
            "room": "228",
            "bldg": "RCE",
            "color": "#ee0639"
        },
        {
            "section_name": "CSCI-160-001",
            "start": "2023-12-08T11:15:00",
            "end": "2023-12-08T12:15:00",
            "faculty1": "Weinberg, Eric G",
            "room": "228",
            "bldg": "RCE",
            "color": "#ee0639"
        },
        {
            "section_name": "CSCI-160-001",
            "start": "2023-12-10T11:15:00",
            "end": "2023-12-10T12:15:00",
            "faculty1": "Weinberg, Eric G",
            "room": "228",
            "bldg": "RCE",
            "color": "#ee0639"
        },
        {
            "section_name": "CSCI-200-001",
            "start": "2023-12-06T12:20:00",
            "end": "2023-12-06T13:20:00",
            "faculty1": "Weinberg, Eric G",
            "room": "228",
            "bldg": "RCE",
            "color": "#ee0639"
        },
        {
            "section_name": "CSCI-200-001",
            "start": "2023-12-08T12:20:00",
            "end": "2023-12-08T13:20:00",
            "faculty1": "Weinberg, Eric G",
            "room": "228",
            "bldg": "RCE",
            "color": "#ee0639"
        },
        {
            "section_name": "CSCI-200-001",
            "start": "2023-12-10T12:20:00",
            "end": "2023-12-10T13:20:00",
            "faculty1": "Weinberg, Eric G",
            "room": "228",
            "bldg": "RCE",
            "color": "#ee0639"
        },
        {
            "section_name": "CSCI-210-001",
            "start": "2023-12-07T14:00:00",
            "end": "2023-12-07T15:30:00",
            "faculty1": "Weinberg, Eric G",
            "room": "228",
            "bldg": "RCE",
            "color": "#ee0639"
        },
        {
            "section_name": "CSCI-210-001",
            "start": "2023-12-09T14:00:00",
            "end": "2023-12-09T15:30:00",
            "faculty1": "Weinberg, Eric G",
            "room": "228",
            "bldg": "RCE",
            "color": "#ee0639"
        },
        {
            "section_name": "CSCI-499-001",
            "start": "2023-12-06T10:10:00",
            "end": "2023-12-06T11:10:00",
            "faculty1": "Weinberg, Eric G",
            "room": "233",
            "bldg": "RCE",
            "color": "#ee0639"
        },
        {
            "section_name": "CSCI-499-001",
            "start": "2023-12-08T10:10:00",
            "end": "2023-12-08T11:10:00",
            "faculty1": "Weinberg, Eric G",
            "room": "233",
            "bldg": "RCE",
            "color": "#ee0639"
        },
        {
            "section_name": "CSCI-499-001",
            "start": "2023-12-10T10:10:00",
            "end": "2023-12-10T11:10:00",
            "faculty1": "Weinberg, Eric G",
            "room": "233",
            "bldg": "RCE",
            "color": "#ee0639"
        },
        {
            "section_name": "ENGR-150-001",
            "start": "2023-12-07T12:30:00",
            "end": "2023-12-07T14:00:00",
            "faculty1": "Vanderfleet, Emily J",
            "room": "438",
            "bldg": "FAC",
            "color": "#67a113"
        },
        {
            "section_name": "ENGR-150-001",
            "start": "2023-12-09T12:30:00",
            "end": "2023-12-09T14:00:00",
            "faculty1": "Vanderfleet, Emily J",
            "room": "438",
            "bldg": "FAC",
            "color": "#67a113"
        },
        {
            "section_name": "ENGR-250-001",
            "start": "2023-12-06T14:30:00",
            "end": "2023-12-06T15:30:00",
            "faculty1": "Harned, Richard C",
            "room": "233",
            "bldg": "RCE",
            "color": "#67a113"
        },
        {
            "section_name": "ENGR-250-001",
            "start": "2023-12-08T14:30:00",
            "end": "2023-12-08T15:30:00",
            "faculty1": "Harned, Richard C",
            "room": "233",
            "bldg": "RCE",
            "color": "#67a113"
        },
        {
            "section_name": "ENGR-250-001",
            "start": "2023-12-10T14:30:00",
            "end": "2023-12-10T15:30:00",
            "faculty1": "Harned, Richard C",
            "room": "233",
            "bldg": "RCE",
            "color": "#67a113"
        },
        {
            "section_name": "ENGR-320-001",
            "start": "2023-12-07T14:00:00",
            "end": "2023-12-07T15:30:00",
            "faculty1": "Vanderfleet, Emily J",
            "room": "233",
            "bldg": "RCE",
            "color": "#67a113"
        },
        {
            "section_name": "ENGR-320-001",
            "start": "2023-12-09T14:00:00",
            "end": "2023-12-09T15:30:00",
            "faculty1": "Vanderfleet, Emily J",
            "room": "233",
            "bldg": "RCE",
            "color": "#67a113"
        },
        {
            "section_name": "ENGR-365-001",
            "start": "2023-12-07T08:00:00",
            "end": "2023-12-07T09:30:00",
            "faculty1": "Lee, Sheldon H",
            "room": "233",
            "bldg": "RCE",
            "color": "#67a113"
        },
        {
            "section_name": "ENGR-365-001",
            "start": "2023-12-09T08:00:00",
            "end": "2023-12-09T09:30:00",
            "faculty1": "Lee, Sheldon H",
            "room": "233",
            "bldg": "RCE",
            "color": "#67a113"
        },
        {
            "section_name": "ENGR-370-001",
            "start": "2023-12-07T15:30:00",
            "end": "2023-12-07T17:00:00",
            "faculty1": "Harned, Richard C",
            "room": "233",
            "bldg": "RCE",
            "color": "#67a113"
        },
        {
            "section_name": "ENGR-370-001",
            "start": "2023-12-09T15:30:00",
            "end": "2023-12-09T17:00:00",
            "faculty1": "Harned, Richard C",
            "room": "233",
            "bldg": "RCE",
            "color": "#67a113"
        },
        {
            "section_name": "ENGR-489-001",
            "start": "2023-12-07T09:30:00",
            "end": "2023-12-07T11:00:00",
            "faculty1": "nan",
            "room": "ARRG",
            "bldg": "ARRG",
            "color": "#67a113"
        },
        {
            "section_name": "ENGR-489-001",
            "start": "2023-12-09T09:30:00",
            "end": "2023-12-09T11:00:00",
            "faculty1": "nan",
            "room": "ARRG",
            "bldg": "ARRG",
            "color": "#67a113"
        },
        {
            "section_name": "ENGR-499-001",
            "start": "2023-12-06T15:35:00",
            "end": "2023-12-06T16:35:00",
            "faculty1": "Harned, Richard C",
            "room": "233",
            "bldg": "RCE",
            "color": "#67a113"
        },
        {
            "section_name": "ENGR-499-001",
            "start": "2023-12-08T15:35:00",
            "end": "2023-12-08T16:35:00",
            "faculty1": "Harned, Richard C",
            "room": "233",
            "bldg": "RCE",
            "color": "#67a113"
        },
        {
            "section_name": "ENGR-499-001",
            "start": "2023-12-10T15:35:00",
            "end": "2023-12-10T16:35:00",
            "faculty1": "Harned, Richard C",
            "room": "233",
            "bldg": "RCE",
            "color": "#67a113"
        },
        {
            "section_name": "MATH-091-001",
            "start": "2023-12-07T15:30:00",
            "end": "2023-12-07T17:00:00",
            "faculty1": "Gaedy, Beth M",
            "room": "314",
            "bldg": "MRC",
            "color": "#65571a"
        },
        {
            "section_name": "MATH-091-001",
            "start": "2023-12-09T15:30:00",
            "end": "2023-12-09T17:00:00",
            "faculty1": "Gaedy, Beth M",
            "room": "314",
            "bldg": "MRC",
            "color": "#65571a"
        },
        {
            "section_name": "MATH-112-001",
            "start": "2023-12-06T09:05:00",
            "end": "2023-12-06T10:05:00",
            "faculty1": "Wodzak, Michael A",
            "room": "346",
            "bldg": "MRC",
            "color": "#65571a"
        },
        {
            "section_name": "MATH-112-001",
            "start": "2023-12-08T09:05:00",
            "end": "2023-12-08T10:05:00",
            "faculty1": "Wodzak, Michael A",
            "room": "346",
            "bldg": "MRC",
            "color": "#65571a"
        },
        {
            "section_name": "MATH-112-001",
            "start": "2023-12-10T09:05:00",
            "end": "2023-12-10T10:05:00",
            "faculty1": "Wodzak, Michael A",
            "room": "346",
            "bldg": "MRC",
            "color": "#65571a"
        },
        {
            "section_name": "MATH-113-001",
            "start": "2023-12-06T15:35:00",
            "end": "2023-12-06T16:35:00",
            "faculty1": "Wodzak, Michael A",
            "room": "346",
            "bldg": "MRC",
            "color": "#65571a"
        },
        {
            "section_name": "MATH-113-001",
            "start": "2023-12-08T15:35:00",
            "end": "2023-12-08T16:35:00",
            "faculty1": "Wodzak, Michael A",
            "room": "346",
            "bldg": "MRC",
            "color": "#65571a"
        },
        {
            "section_name": "MATH-113-001",
            "start": "2023-12-10T15:35:00",
            "end": "2023-12-10T16:35:00",
            "faculty1": "Wodzak, Michael A",
            "room": "346",
            "bldg": "MRC",
            "color": "#65571a"
        },
        {
            "section_name": "MATH-130-001",
            "start": "2023-12-06T09:05:00",
            "end": "2023-12-06T10:05:00",
            "faculty1": "TBD",
            "room": "314",
            "bldg": "MRC",
            "color": "#65571a"
        },
        {
            "section_name": "MATH-130-001",
            "start": "2023-12-08T09:05:00",
            "end": "2023-12-08T10:05:00",
            "faculty1": "TBD",
            "room": "314",
            "bldg": "MRC",
            "color": "#65571a"
        },
        {
            "section_name": "MATH-130-001",
            "start": "2023-12-10T09:05:00",
            "end": "2023-12-10T10:05:00",
            "faculty1": "TBD",
            "room": "314",
            "bldg": "MRC",
            "color": "#65571a"
        },
        {
            "section_name": "MATH-130-002",
            "start": "2023-12-06T14:30:00",
            "end": "2023-12-06T15:30:00",
            "faculty1": "TBD",
            "room": "nan",
            "bldg": "nan",
            "color": "#65571a"
        },
        {
            "section_name": "MATH-130-002",
            "start": "2023-12-08T14:30:00",
            "end": "2023-12-08T15:30:00",
            "faculty1": "TBD",
            "room": "nan",
            "bldg": "nan",
            "color": "#65571a"
        },
        {
            "section_name": "MATH-130-002",
            "start": "2023-12-10T14:30:00",
            "end": "2023-12-10T15:30:00",
            "faculty1": "TBD",
            "room": "nan",
            "bldg": "nan",
            "color": "#65571a"
        },
        {
            "section_name": "MATH-155-001",
            "start": "2023-12-06T10:10:00",
            "end": "2023-12-06T11:10:00",
            "faculty1": "Wodzak, Michael A",
            "room": "378",
            "bldg": "MRC",
            "color": "#65571a"
        },
        {
            "section_name": "MATH-155-001",
            "start": "2023-12-08T10:10:00",
            "end": "2023-12-08T11:10:00",
            "faculty1": "Wodzak, Michael A",
            "room": "378",
            "bldg": "MRC",
            "color": "#65571a"
        },
        {
            "section_name": "MATH-155-001",
            "start": "2023-12-10T10:10:00",
            "end": "2023-12-10T11:10:00",
            "faculty1": "Wodzak, Michael A",
            "room": "378",
            "bldg": "MRC",
            "color": "#65571a"
        },
        {
            "section_name": "MATH-221-001",
            "start": "2023-12-06T12:20:00",
            "end": "2023-12-06T13:20:00",
            "faculty1": "Lee, Sheldon H",
            "room": "444",
            "bldg": "MRC",
            "color": "#65571a"
        },
        {
            "section_name": "MATH-221-001",
            "start": "2023-12-08T12:20:00",
            "end": "2023-12-08T13:20:00",
            "faculty1": "Lee, Sheldon H",
            "room": "444",
            "bldg": "MRC",
            "color": "#65571a"
        },
        {
            "section_name": "MATH-221-001",
            "start": "2023-12-10T12:20:00",
            "end": "2023-12-10T13:20:00",
            "faculty1": "Lee, Sheldon H",
            "room": "444",
            "bldg": "MRC",
            "color": "#65571a"
        },
        {
            "section_name": "MATH-230-001",
            "start": "2023-12-07T11:00:00",
            "end": "2023-12-07T12:30:00",
            "faculty1": "Lee, Sheldon H",
            "room": "314",
            "bldg": "MRC",
            "color": "#65571a"
        },
        {
            "section_name": "MATH-230-001",
            "start": "2023-12-09T11:00:00",
            "end": "2023-12-09T12:30:00",
            "faculty1": "Lee, Sheldon H",
            "room": "314",
            "bldg": "MRC",
            "color": "#65571a"
        },
        {
            "section_name": "MATH-255-001",
            "start": "2023-12-06T10:10:00",
            "end": "2023-12-06T11:10:00",
            "faculty1": "Lichty, Joshua J",
            "room": "416",
            "bldg": "MRC",
            "color": "#65571a"
        },
        {
            "section_name": "MATH-255-001",
            "start": "2023-12-08T10:10:00",
            "end": "2023-12-08T11:10:00",
            "faculty1": "Lichty, Joshua J",
            "room": "416",
            "bldg": "MRC",
            "color": "#65571a"
        },
        {
            "section_name": "MATH-255-001",
            "start": "2023-12-10T10:10:00",
            "end": "2023-12-10T11:10:00",
            "faculty1": "Lichty, Joshua J",
            "room": "416",
            "bldg": "MRC",
            "color": "#65571a"
        },
        {
            "section_name": "MATH-270-001",
            "start": "2023-12-07T08:00:00",
            "end": "2023-12-07T09:30:00",
            "faculty1": "Wodzak, Michael A",
            "room": "444",
            "bldg": "MRC",
            "color": "#65571a"
        },
        {
            "section_name": "MATH-270-001",
            "start": "2023-12-09T08:00:00",
            "end": "2023-12-09T09:30:00",
            "faculty1": "Wodzak, Michael A",
            "room": "444",
            "bldg": "MRC",
            "color": "#65571a"
        },
        {
            "section_name": "MATH-344-001",
            "start": "2023-12-07T09:30:00",
            "end": "2023-12-07T11:00:00",
            "faculty1": "Wodzak, Michael A",
            "room": "378",
            "bldg": "MRC",
            "color": "#65571a"
        },
        {
            "section_name": "MATH-344-001",
            "start": "2023-12-09T09:30:00",
            "end": "2023-12-09T11:00:00",
            "faculty1": "Wodzak, Michael A",
            "room": "378",
            "bldg": "MRC",
            "color": "#65571a"
        },
        {
            "section_name": "MATH-365-001",
            "start": "2023-12-06T13:25:00",
            "end": "2023-12-06T14:25:00",
            "faculty1": "Lee, Sheldon H",
            "room": "233",
            "bldg": "RCE",
            "color": "#65571a"
        },
        {
            "section_name": "MATH-365-001",
            "start": "2023-12-08T13:25:00",
            "end": "2023-12-08T14:25:00",
            "faculty1": "Lee, Sheldon H",
            "room": "233",
            "bldg": "RCE",
            "color": "#65571a"
        },
        {
            "section_name": "MATH-365-001",
            "start": "2023-12-10T13:25:00",
            "end": "2023-12-10T14:25:00",
            "faculty1": "Lee, Sheldon H",
            "room": "233",
            "bldg": "RCE",
            "color": "#65571a"
        },
        {
            "section_name": "MATH-499-001",
            "start": "2023-12-07T09:30:00",
            "end": "2023-12-07T11:00:00",
            "faculty1": "Lee, Sheldon H",
            "room": "233",
            "bldg": "RCE",
            "color": "#65571a"
        },
        {
            "section_name": "MATH-499-001",
            "start": "2023-12-09T09:30:00",
            "end": "2023-12-09T11:00:00",
            "faculty1": "Lee, Sheldon H",
            "room": "233",
            "bldg": "RCE",
            "color": "#65571a"
        },
        {
            "section_name": "PHYS-102-001",
            "start": "2023-12-06T08:00:00",
            "end": "2023-12-06T09:00:00",
            "faculty1": "Narayanan, Madhavan",
            "room": "229",
            "bldg": "RCE",
            "color": "#ce6df7"
        },
        {
            "section_name": "PHYS-102-001",
            "start": "2023-12-08T08:00:00",
            "end": "2023-12-08T09:00:00",
            "faculty1": "Narayanan, Madhavan",
            "room": "229",
            "bldg": "RCE",
            "color": "#ce6df7"
        },
        {
            "section_name": "PHYS-102-001",
            "start": "2023-12-10T08:00:00",
            "end": "2023-12-10T09:00:00",
            "faculty1": "Narayanan, Madhavan",
            "room": "229",
            "bldg": "RCE",
            "color": "#ce6df7"
        },
        {
            "section_name": "PHYS-251-001",
            "start": "2023-12-06T15:35:00",
            "end": "2023-12-06T16:35:00",
            "faculty1": "Gerig, Anthony L",
            "room": "229",
            "bldg": "RCE",
            "color": "#ce6df7"
        },
        {
            "section_name": "PHYS-251-001",
            "start": "2023-12-08T15:35:00",
            "end": "2023-12-08T16:35:00",
            "faculty1": "Gerig, Anthony L",
            "room": "229",
            "bldg": "RCE",
            "color": "#ce6df7"
        },
        {
            "section_name": "PHYS-251-001",
            "start": "2023-12-10T15:35:00",
            "end": "2023-12-10T16:35:00",
            "faculty1": "Gerig, Anthony L",
            "room": "229",
            "bldg": "RCE",
            "color": "#ce6df7"
        },
        {
            "section_name": "PHYS-261-001",
            "start": "2023-12-06T09:05:00",
            "end": "2023-12-06T10:05:00",
            "faculty1": "Anglehart, Joseph",
            "room": "229",
            "bldg": "RCE",
            "color": "#ce6df7"
        },
        {
            "section_name": "PHYS-261-001",
            "start": "2023-12-08T09:05:00",
            "end": "2023-12-08T10:05:00",
            "faculty1": "Anglehart, Joseph",
            "room": "229",
            "bldg": "RCE",
            "color": "#ce6df7"
        },
        {
            "section_name": "PHYS-261-001",
            "start": "2023-12-10T09:05:00",
            "end": "2023-12-10T10:05:00",
            "faculty1": "Anglehart, Joseph",
            "room": "229",
            "bldg": "RCE",
            "color": "#ce6df7"
        },
        {
            "section_name": "CSCI-160-001_one_credit",
            "start": "2023-12-09T11:00:00",
            "end": "2023-12-09T12:30:00",
            "faculty1": "Weinberg, Eric G",
            "room": "228",
            "bldg": "RCE",
            "color": "#ee0639"
        },
        {
            "section_name": "ENGR-150-001_one_credit",
            "start": "2023-12-10T08:00:00",
            "end": "2023-12-10T09:30:00",
            "faculty1": "Vanderfleet, Emily J",
            "room": "438",
            "bldg": "FAC",
            "color": "#67a113"
        },
        {
            "section_name": "ENGR-250-001_one_credit",
            "start": "2023-12-07T15:30:00",
            "end": "2023-12-07T17:00:00",
            "faculty1": "Harned, Richard C",
            "room": "233",
            "bldg": "RCE",
            "color": "#67a113"
        },
        {
            "section_name": "ENGR-320-001_one_credit",
            "start": "2023-12-08T08:00:00",
            "end": "2023-12-08T09:30:00",
            "faculty1": "Vanderfleet, Emily J",
            "room": "233",
            "bldg": "RCE",
            "color": "#67a113"
        },
        {
            "section_name": "ENGR-365-001_one_credit",
            "start": "2023-12-10T09:05:00",
            "end": "2023-12-10T10:35:00",
            "faculty1": "Lee, Sheldon H",
            "room": "233",
            "bldg": "RCE",
            "color": "#67a113"
        },
        {
            "section_name": "ENGR-370-001_one_credit",
            "start": "2023-12-09T08:00:00",
            "end": "2023-12-09T09:30:00",
            "faculty1": "Harned, Richard C",
            "room": "233",
            "bldg": "RCE",
            "color": "#67a113"
        },
        {
            "section_name": "MATH-081-001",
            "start": "2023-12-08T12:20:00",
            "end": "2023-12-08T13:50:00",
            "faculty1": "Gaedy, Beth M",
            "room": "378",
            "bldg": "MRC",
            "color": "#65571a"
        },
        {
            "section_name": "MATH-083-001",
            "start": "2023-12-08T10:10:00",
            "end": "2023-12-08T11:40:00",
            "faculty1": "Gaedy, Beth M",
            "room": "378",
            "bldg": "MRC",
            "color": "#65571a"
        },
        {
            "section_name": "MATH-150-001",
            "start": "2023-12-09T12:30:00",
            "end": "2023-12-09T14:00:00",
            "faculty1": "Vanderfleet, Emily J",
            "room": "285",
            "bldg": "NRC",
            "color": "#65571a"
        },
        {
            "section_name": "MATH-221-001_one_credit",
            "start": "2023-12-10T13:25:00",
            "end": "2023-12-10T14:55:00",
            "faculty1": "Lee, Sheldon H",
            "room": "444",
            "bldg": "MRC",
            "color": "#65571a"
        },
        {
            "section_name": "MATH-230-001_one_credit",
            "start": "2023-12-06T14:30:00",
            "end": "2023-12-06T16:00:00",
            "faculty1": "Lee, Sheldon H",
            "room": "314",
            "bldg": "MRC",
            "color": "#65571a"
        },
        {
            "section_name": "MATH-365-001_one_credit",
            "start": "2023-12-07T12:30:00",
            "end": "2023-12-07T14:00:00",
            "faculty1": "Lee, Sheldon H",
            "room": "233",
            "bldg": "RCE",
            "color": "#65571a"
        },
        {
            "section_name": "PHYS-102-001_one_credit",
            "start": "2023-12-10T11:15:00",
            "end": "2023-12-10T12:45:00",
            "faculty1": "Narayanan, Madhavan",
            "room": "229",
            "bldg": "RCE",
            "color": "#ce6df7"
        },
        {
            "section_name": "PHYS-271-001",
            "start": "2023-12-08T13:25:00",
            "end": "2023-12-08T14:55:00",
            "faculty1": "Anglehart, Joseph",
            "room": "229",
            "bldg": "RCE",
            "color": "#ce6df7"
        }
    ],
    "message": "Optimization completed"
}